iprotopy/__init__.py
iprotopy/annotation_generator.py
iprotopy/astor_parse.py
iprotopy/base_service_source_generator.py
iprotopy/class_field_generator.py
iprotopy/constants.py
iprotopy/convertion.py
iprotopy/domestic_importer.py
iprotopy/enum_generator.py
iprotopy/file_generator.py
iprotopy/import_types.py
iprotopy/importer.py
iprotopy/imports.py
iprotopy/message_class_generator.py
iprotopy/one_of_generator.py
iprotopy/package_generator.py
iprotopy/protos_generator.py
iprotopy/service_generator.py
iprotopy/service_method_generator.py
iprotopy/type_mapper.py
iprotopy-0.3.0.dist-info/METADATA
iprotopy-0.3.0.dist-info/WHEEL
iprotopy-0.3.0.dist-info/RECORD
